im_remind/__init__.py
im_remind/__main__.py
im_remind/core.py
im_remind-1.0.2.data/scripts/im-remind
im_remind-1.0.2.dist-info/LICENSE
im_remind-1.0.2.dist-info/METADATA
im_remind-1.0.2.dist-info/WHEEL
im_remind-1.0.2.dist-info/top_level.txt
im_remind-1.0.2.dist-info/RECORD
