Metadata-Version: 2.1
Name: im-remind
Version: 1.0.2
Summary: A simple tool for reminding you on IM.
Home-page: https://github.com/leonardodalinky/im-remind
Author: leonardodalink
Author-email: ayajilin@pm.me
Project-URL: Tracker, https://github.com/leonardodalinky/im-remind/issues
Project-URL: Source, https://github.com/leonardodalinky/im-remind
Keywords: qq telegram
Classifier: Development Status :: 3 - Alpha
Classifier: Programming Language :: Python :: 3
Classifier: License :: OSI Approved :: MIT License
Classifier: Operating System :: OS Independent
Classifier: Natural Language :: English
Requires-Python: >=3.6
License-File: LICENSE
Requires-Dist: requests (>=2)
Requires-Dist: PyYAML
